{
    "url": "https://www.emol.com/noticias/Deportes/2016/12/08/834699/Presidente-de-la-FIFA-pidio-tolerancia-cero-ante-los-abusos-sexuales-que-han-sido-denunciados-en-Inglaterra.html",
    "title": "Presidente de la FIFA pidió \"tolerancia cero\" ante los abusos sexuales denunciados en Inglaterra",
    "subhead": "Las palabras de Gianni Infantino se producen después que la Federación Inglesa haya emprendido una investigación tras las denuncias hechas por más de 300 futbolistas.",
    "date": "08 de Diciembre de 2016",
    "time": "13:16",
    "agency": "Emol/EFE",
    "text": "SANTIAGO.- El presidente de la FIFA, Gianni Infantino, pidió \"tolerancia cero\" ante los abusos sexuales que pueden sufrir los jugadores jóvenes y se comprometió a buscar fórmulas para que la FIFA puede hacer más para prevenirlos, tras las denuncias hechas ahora por futbolistas ingleses. \"Hay que afrontarlo con mucha seriedad. Debe haber tolerancia cero desde la perspectiva del fútbol y también desde una perspectiva criminal\", aseguró Infantino en Singapur en declaraciones a los medios de comunicación. Las palabras del presidente de la FIFA se producen después de que la Federación Inglesa (FA) haya emprendido una investigación tras las denuncias hechas por más de 300 futbolistas que ahora aseguraron haber sido víctimas de abusos sexuales cuando eran niños por parte de entrenadores y ojeadores. \"Los que sean culpables de haber abusado de niños tienen que ser castigados muy seriamente. Tienen que quedarse fuera del fútbol sin ninguna duda, pero en el plano criminal también deben recibir un castigo\", añadió el dirigente suizo. Infantino se refirió a las actuaciones que lleva a cabo la FA sobre el caso, que debe afrontarse \"muy seriamente\", y aludió a la necesidad de que la FIFA intente hacer algo en materia de prevención. ",
    "comments_url": "https://cache-comentarios.ecn.cl/Comments/Api?action=getComments&url=https%3A%2F%2Fwww.emol.com%2Fnoticias%2FDeportes%2F2016%2F12%2F08%2F834699%2FPresidente-de-la-FIFA-pidio-tolerancia-cero-ante-los-abusos-sexuales-que-han-sido-denunciados-en-Inglaterra.html&includePending=true&format=json&limit=0&order=TIME_DESC&rootComment=true",
    "comments": [
        {
            "id": 2388674,
            "avatar": "https://imgcomentarista.emol.cl/images/54/38154_1537669356614.jpg",
            "creator": "Christian Cortes",
            "presence": "AWAY",
            "promotedCreator": false,
            "creatorId": 38154,
            "banned": false,
            "authSource": "facebook",
            "validated": false,
            "text": "&nbsp;Sandy???",
            "likes": 0,
            "dislikes": 0,
            "denounces": 0,
            "time": 1481230614000,
            "status": "NEW",
            "boost": 0,
            "highlight": false,
            "level": 0,
            "pageSection": "Deportes",
            "anchor": "C",
            "pageCmsId": 834699
        },
        {
            "id": 2388590,
            "avatar": "https://imgcomentarista.emol.cl/images/8/25108_1541840284613.jpg",
            "creator": "Joaquin Fernandez Fuentes",
            "presence": "AWAY",
            "promotedCreator": false,
            "creatorId": 25108,
            "banned": false,
            "authSource": "facebook",
            "validated": false,
            "text": "&nbsp;lex luthor",
            "likes": 0,
            "dislikes": 0,
            "denounces": 0,
            "time": 1481229849000,
            "status": "NEW",
            "boost": 0,
            "highlight": false,
            "level": 0,
            "pageSection": "Deportes",
            "anchor": "C",
            "pageCmsId": 834699
        },
        {
            "id": 2387459,
            "avatar": "https://imgcomentarista.emol.cl/images/37/210737_1543239677067.jpg",
            "creator": "Dann Agu Val",
            "presence": "AWAY",
            "promotedCreator": false,
            "creatorId": 210737,
            "banned": false,
            "authSource": "facebook",
            "validated": false,
            "text": "&nbsp;Es idea mía o se parece al humorista sandi?",
            "likes": 0,
            "dislikes": 0,
            "denounces": 0,
            "time": 1481214517000,
            "status": "NEW",
            "boost": 0,
            "highlight": false,
            "level": 0,
            "pageSection": "Deportes",
            "anchor": "C",
            "pageCmsId": 834699
        },
        {
            "id": 2387344,
            "avatar": "https://imgcomentarista.emol.cl/images/74/26874_1541792224859.jpg",
            "creator": "JubicaDe Lourdes Bowers",
            "presence": "AWAY",
            "promotedCreator": false,
            "creatorId": 26874,
            "banned": false,
            "authSource": "facebook",
            "validated": false,
            "text": "&nbsp;Desgraciados asquerosos,, Hay que advertir a los jovenes de esta lacra asquerosa,,, empiezan con miraditas raras, a hacer tocaciones si alguno acepta,,, inmediatamente darle patadas en las guevas, y denunciarlos sin miedo,,,porque estos amenazan, pero no hacen nada,,, es pura boca. A la carcel esta bestias mal paridas.",
            "likes": 0,
            "dislikes": 0,
            "denounces": 0,
            "time": 1481212886000,
            "status": "NEW",
            "boost": 0,
            "highlight": false,
            "level": 0,
            "pageSection": "Deportes",
            "anchor": "C",
            "pageCmsId": 834699
        },
        {
            "id": 2386924,
            "avatar": "https://imgcomentarista.emol.cl/images/44/1344_1540753769072.jpg",
            "creator": "Luis Briones Milla",
            "presence": "AWAY",
            "promotedCreator": false,
            "creatorId": 1344,
            "banned": false,
            "authSource": "facebook",
            "validated": false,
            "text": "&nbsp;LA LECHE ESTÁ DERRAMADA. EL DAÑO ESTÁ HECHO Y DEBE SER SANCIONADO. PERO ES IMPRESENTABLE QUE LA FIFA NO HAGA NADA PARA P R E V E N I R LOS ABUSOS SEXUALES. CRIMINALES DEL SEXO HAY EN TODOS LADOS , en todas las épocas , en todos los lugares y en todas las instituciones.",
            "likes": 0,
            "dislikes": 0,
            "denounces": 0,
            "time": 1481205813000,
            "status": "NEW",
            "boost": 0,
            "highlight": false,
            "level": 0,
            "pageSection": "Deportes",
            "anchor": "C",
            "pageCmsId": 834699
        },
        {
            "id": 2387322,
            "avatar": "https://imgcomentarista.emol.cl/images/74/26874_1541792224859.jpg",
            "creator": "JubicaDe Lourdes Bowers",
            "presence": "AWAY",
            "promotedCreator": false,
            "creatorId": 26874,
            "parentId": 2386924,
            "parentCreatorId": 1344,
            "banned": false,
            "authSource": "facebook",
            "validated": false,
            "text": "&nbsp;Tienes toda la razon ,,, estan en todos lados esos criminales del sexo. Investigar, a a fondo,, dar a conocer sus nombres, poner las fotos, para que todo el mundo los vea tan depravados que son. Carcel , carcel al instante.. No les gusto hacer la maldad?? que paguenn",
            "likes": 0,
            "dislikes": 0,
            "denounces": 0,
            "time": 1481212550000,
            "status": "NEW",
            "boost": 0,
            "highlight": false,
            "level": 1,
            "pageSection": "Deportes",
            "anchor": "C",
            "pageCmsId": 834699
        }
    ]
}